cai_causal_fairness/__init__.py
cai_causal_fairness-0.0.0.dist-info/WHEEL
cai_causal_fairness-0.0.0.dist-info/METADATA
cai_causal_fairness-0.0.0.dist-info/RECORD
