Metadata-Version: 2.1
Name: cai-causal-fairness
Version: 0.0.0
Summary: Quantify the algorithmic fairness and fix potential unfairness of an ML model.
Author: causaLens
Author-email: opensource@causalens.com
Requires-Python: >=3.8,<4.0
Classifier: Programming Language :: Python :: 3
Classifier: Programming Language :: Python :: 3.8
Classifier: Programming Language :: Python :: 3.9
Classifier: Programming Language :: Python :: 3.10
Classifier: Programming Language :: Python :: 3.11
